{
  "updatedAt": "2026-04-20T23:00:04.812853+00:00",
  "source": "kurorunner",
  "version": 1,
  "job_id": "kurotrader-health",
  "runs": [
    {
      "ts": "2026-04-20T23:00:03.392400+00:00",
      "exit": 0,
      "duration_ms": 29,
      "tokens_in": 0,
      "tokens_out": 0,
      "consecutive_errors": 0,
      "error": null
    },
    {
      "ts": "2026-04-20T22:55:02.679117+00:00",
      "exit": 0,
      "duration_ms": 34,
      "tokens_in": 0,
      "tokens_out": 0,
      "consecutive_errors": 0,
      "error": null
    },
    {
      "ts": "2026-04-20T22:50:05.669866+00:00",
      "exit": 0,
      "duration_ms": 30,
      "tokens_in": 0,
      "tokens_out": 0,
      "consecutive_errors": 0,
      "error": null
    },
    {
      "ts": "2026-04-20T22:45:01.910182+00:00",
      "exit": 0,
      "duration_ms": 34,
      "tokens_in": 0,
      "tokens_out": 0,
      "consecutive_errors": 0,
      "error": null
    },
    {
      "ts": "2026-04-20T22:40:01.173674+00:00",
      "exit": 0,
      "duration_ms": 34,
      "tokens_in": 0,
      "tokens_out": 0,
      "consecutive_errors": 0,
      "error": null
    },
    {
      "ts": "2026-04-20T22:35:03.912412+00:00",
      "exit": 0,
      "duration_ms": 34,
      "tokens_in": 0,
      "tokens_out": 0,
      "consecutive_errors": 0,
      "error": null
    },
    {
      "ts": "2026-04-20T22:30:06.924055+00:00",
      "exit": 0,
      "duration_ms": 35,
      "tokens_in": 0,
      "tokens_out": 0,
      "consecutive_errors": 0,
      "error": null
    },
    {
      "ts": "2026-04-20T22:25:02.901710+00:00",
      "exit": 0,
      "duration_ms": 34,
      "tokens_in": 0,
      "tokens_out": 0,
      "consecutive_errors": 0,
      "error": null
    },
    {
      "ts": "2026-04-20T22:20:02.246268+00:00",
      "exit": 0,
      "duration_ms": 35,
      "tokens_in": 0,
      "tokens_out": 0,
      "consecutive_errors": 0,
      "error": null
    },
    {
      "ts": "2026-04-20T22:15:05.158188+00:00",
      "exit": 0,
      "duration_ms": 32,
      "tokens_in": 0,
      "tokens_out": 0,
      "consecutive_errors": 0,
      "error": null
    },
    {
      "ts": "2026-04-20T22:10:01.190672+00:00",
      "exit": 0,
      "duration_ms": 34,
      "tokens_in": 0,
      "tokens_out": 0,
      "consecutive_errors": 0,
      "error": null
    },
    {
      "ts": "2026-04-20T22:05:00.668728+00:00",
      "exit": 0,
      "duration_ms": 33,
      "tokens_in": 0,
      "tokens_out": 0,
      "consecutive_errors": 0,
      "error": null
    },
    {
      "ts": "2026-04-20T22:00:03.398114+00:00",
      "exit": 0,
      "duration_ms": 29,
      "tokens_in": 0,
      "tokens_out": 0,
      "consecutive_errors": 0,
      "error": null
    },
    {
      "ts": "2026-04-20T21:55:02.904462+00:00",
      "exit": 0,
      "duration_ms": 35,
      "tokens_in": 0,
      "tokens_out": 0,
      "consecutive_errors": 0,
      "error": null
    },
    {
      "ts": "2026-04-20T21:50:02.437457+00:00",
      "exit": 0,
      "duration_ms": 34,
      "tokens_in": 0,
      "tokens_out": 0,
      "consecutive_errors": 0,
      "error": null
    },
    {
      "ts": "2026-04-20T21:45:01.910838+00:00",
      "exit": 0,
      "duration_ms": 33,
      "tokens_in": 0,
      "tokens_out": 0,
      "consecutive_errors": 0,
      "error": null
    },
    {
      "ts": "2026-04-20T21:40:04.906795+00:00",
      "exit": 0,
      "duration_ms": 35,
      "tokens_in": 0,
      "tokens_out": 0,
      "consecutive_errors": 0,
      "error": null
    },
    {
      "ts": "2026-04-20T21:35:00.909128+00:00",
      "exit": 0,
      "duration_ms": 34,
      "tokens_in": 0,
      "tokens_out": 0,
      "consecutive_errors": 0,
      "error": null
    },
    {
      "ts": "2026-04-20T21:30:00.401601+00:00",
      "exit": 0,
      "duration_ms": 29,
      "tokens_in": 0,
      "tokens_out": 0,
      "consecutive_errors": 0,
      "error": null
    },
    {
      "ts": "2026-04-20T21:25:03.169505+00:00",
      "exit": 0,
      "duration_ms": 35,
      "tokens_in": 0,
      "tokens_out": 0,
      "consecutive_errors": 0,
      "error": null
    }
  ]
}
