{
  "updatedAt": "2026-04-23T18:40:00.747832+00:00",
  "source": "kurorunner",
  "version": 1,
  "job_id": "git-autocommit",
  "runs": [
    {
      "ts": "2026-04-23T18:37:03.542322+00:00",
      "exit": 0,
      "duration_ms": 1339,
      "tokens_in": 0,
      "tokens_out": 0,
      "consecutive_errors": 0,
      "error": null
    },
    {
      "ts": "2026-04-23T18:27:03.252156+00:00",
      "exit": 0,
      "duration_ms": 1295,
      "tokens_in": 0,
      "tokens_out": 0,
      "consecutive_errors": 0,
      "error": null
    },
    {
      "ts": "2026-04-23T18:17:00.787221+00:00",
      "exit": 0,
      "duration_ms": 1221,
      "tokens_in": 0,
      "tokens_out": 0,
      "consecutive_errors": 0,
      "error": null
    },
    {
      "ts": "2026-04-23T18:07:00.221318+00:00",
      "exit": 0,
      "duration_ms": 1272,
      "tokens_in": 0,
      "tokens_out": 0,
      "consecutive_errors": 0,
      "error": null
    },
    {
      "ts": "2026-04-23T17:56:59.098417+00:00",
      "exit": 0,
      "duration_ms": 1389,
      "tokens_in": 0,
      "tokens_out": 0,
      "consecutive_errors": 0,
      "error": null
    },
    {
      "ts": "2026-04-23T17:46:56.247402+00:00",
      "exit": 0,
      "duration_ms": 1283,
      "tokens_in": 0,
      "tokens_out": 0,
      "consecutive_errors": 0,
      "error": null
    },
    {
      "ts": "2026-04-23T17:36:54.315177+00:00",
      "exit": 0,
      "duration_ms": 1355,
      "tokens_in": 0,
      "tokens_out": 0,
      "consecutive_errors": 0,
      "error": null
    },
    {
      "ts": "2026-04-23T17:26:52.304124+00:00",
      "exit": 0,
      "duration_ms": 1351,
      "tokens_in": 0,
      "tokens_out": 0,
      "consecutive_errors": 0,
      "error": null
    },
    {
      "ts": "2026-04-23T17:16:48.415479+00:00",
      "exit": 0,
      "duration_ms": 1460,
      "tokens_in": 0,
      "tokens_out": 0,
      "consecutive_errors": 0,
      "error": null
    },
    {
      "ts": "2026-04-23T17:06:44.196277+00:00",
      "exit": 0,
      "duration_ms": 1236,
      "tokens_in": 0,
      "tokens_out": 0,
      "consecutive_errors": 0,
      "error": null
    },
    {
      "ts": "2026-04-23T16:56:40.112780+00:00",
      "exit": 0,
      "duration_ms": 1162,
      "tokens_in": 0,
      "tokens_out": 0,
      "consecutive_errors": 0,
      "error": null
    },
    {
      "ts": "2026-04-23T16:46:36.315917+00:00",
      "exit": 0,
      "duration_ms": 1351,
      "tokens_in": 0,
      "tokens_out": 0,
      "consecutive_errors": 0,
      "error": null
    },
    {
      "ts": "2026-04-23T16:36:35.365569+00:00",
      "exit": 0,
      "duration_ms": 1412,
      "tokens_in": 0,
      "tokens_out": 0,
      "consecutive_errors": 0,
      "error": null
    },
    {
      "ts": "2026-04-23T16:26:39.099183+00:00",
      "exit": 0,
      "duration_ms": 6136,
      "tokens_in": 0,
      "tokens_out": 0,
      "consecutive_errors": 0,
      "error": null
    },
    {
      "ts": "2026-04-23T16:16:33.214613+00:00",
      "exit": 0,
      "duration_ms": 1260,
      "tokens_in": 0,
      "tokens_out": 0,
      "consecutive_errors": 0,
      "error": null
    },
    {
      "ts": "2026-04-23T16:06:30.312934+00:00",
      "exit": 0,
      "duration_ms": 2360,
      "tokens_in": 0,
      "tokens_out": 0,
      "consecutive_errors": 0,
      "error": null
    },
    {
      "ts": "2026-04-23T15:56:24.351837+00:00",
      "exit": 0,
      "duration_ms": 1392,
      "tokens_in": 0,
      "tokens_out": 0,
      "consecutive_errors": 0,
      "error": null
    },
    {
      "ts": "2026-04-23T15:46:20.205399+00:00",
      "exit": 0,
      "duration_ms": 1253,
      "tokens_in": 0,
      "tokens_out": 0,
      "consecutive_errors": 0,
      "error": null
    },
    {
      "ts": "2026-04-23T15:36:14.231155+00:00",
      "exit": 0,
      "duration_ms": 1267,
      "tokens_in": 0,
      "tokens_out": 0,
      "consecutive_errors": 0,
      "error": null
    },
    {
      "ts": "2026-04-23T15:26:11.316977+00:00",
      "exit": 0,
      "duration_ms": 1368,
      "tokens_in": 0,
      "tokens_out": 0,
      "consecutive_errors": 0,
      "error": null
    }
  ]
}
