{
  "updatedAt": "2026-04-25T20:56:05Z",
  "source": "goku-health-daemon",
  "version": 1,
  "data": {
    "timeline": [
      {
        "timestamp": "2026-04-25T16:59:36Z",
        "cpuPct": 0.0,
        "memoryPct": 8.2,
        "diskPct": 53.0,
        "gpuTempC": 37.0,
        "gpuVramPct": 91.9
      },
      {
        "timestamp": "2026-04-25T17:04:37Z",
        "cpuPct": 0.0,
        "memoryPct": 8.2,
        "diskPct": 53.0,
        "gpuTempC": 37.0,
        "gpuVramPct": 91.9
      },
      {
        "timestamp": "2026-04-25T17:09:40Z",
        "cpuPct": 0.0,
        "memoryPct": 8.3,
        "diskPct": 53.0,
        "gpuTempC": 38.0,
        "gpuVramPct": 91.9
      },
      {
        "timestamp": "2026-04-25T17:14:42Z",
        "cpuPct": 0.3,
        "memoryPct": 8.3,
        "diskPct": 53.0,
        "gpuTempC": 36.0,
        "gpuVramPct": 91.9
      },
      {
        "timestamp": "2026-04-25T17:19:44Z",
        "cpuPct": 3.6,
        "memoryPct": 8.3,
        "diskPct": 53.0,
        "gpuTempC": 53.0,
        "gpuVramPct": 91.9
      },
      {
        "timestamp": "2026-04-25T17:24:46Z",
        "cpuPct": 0.0,
        "memoryPct": 8.0,
        "diskPct": 53.0,
        "gpuTempC": 38.0,
        "gpuVramPct": 91.9
      },
      {
        "timestamp": "2026-04-25T17:29:48Z",
        "cpuPct": 9.0,
        "memoryPct": 9.6,
        "diskPct": 53.0,
        "gpuTempC": 35.0,
        "gpuVramPct": 91.9
      },
      {
        "timestamp": "2026-04-25T17:34:51Z",
        "cpuPct": 0.0,
        "memoryPct": 8.0,
        "diskPct": 53.0,
        "gpuTempC": 36.0,
        "gpuVramPct": 91.9
      },
      {
        "timestamp": "2026-04-25T17:39:53Z",
        "cpuPct": 0.0,
        "memoryPct": 8.0,
        "diskPct": 53.0,
        "gpuTempC": 35.0,
        "gpuVramPct": 91.9
      },
      {
        "timestamp": "2026-04-25T17:44:55Z",
        "cpuPct": 0.0,
        "memoryPct": 8.0,
        "diskPct": 53.0,
        "gpuTempC": 41.0,
        "gpuVramPct": 91.9
      },
      {
        "timestamp": "2026-04-25T17:49:56Z",
        "cpuPct": 0.0,
        "memoryPct": 7.9,
        "diskPct": 53.0,
        "gpuTempC": 39.0,
        "gpuVramPct": 91.9
      },
      {
        "timestamp": "2026-04-25T17:54:59Z",
        "cpuPct": 0.0,
        "memoryPct": 8.0,
        "diskPct": 53.0,
        "gpuTempC": 37.0,
        "gpuVramPct": 91.9
      },
      {
        "timestamp": "2026-04-25T18:00:00Z",
        "cpuPct": 6.9,
        "memoryPct": 8.1,
        "diskPct": 53.0,
        "gpuTempC": 37.0,
        "gpuVramPct": 91.9
      },
      {
        "timestamp": "2026-04-25T18:05:00Z",
        "cpuPct": 4.8,
        "memoryPct": 8.2,
        "diskPct": 53.0,
        "gpuTempC": 61.0,
        "gpuVramPct": 91.9
      },
      {
        "timestamp": "2026-04-25T18:10:01Z",
        "cpuPct": 0.3,
        "memoryPct": 8.1,
        "diskPct": 53.0,
        "gpuTempC": 40.0,
        "gpuVramPct": 91.9
      },
      {
        "timestamp": "2026-04-25T18:15:04Z",
        "cpuPct": 3.6,
        "memoryPct": 8.1,
        "diskPct": 53.0,
        "gpuTempC": 37.0,
        "gpuVramPct": 91.9
      },
      {
        "timestamp": "2026-04-25T18:20:05Z",
        "cpuPct": 0.3,
        "memoryPct": 8.0,
        "diskPct": 53.0,
        "gpuTempC": 37.0,
        "gpuVramPct": 91.9
      },
      {
        "timestamp": "2026-04-25T18:25:06Z",
        "cpuPct": 0.0,
        "memoryPct": 8.0,
        "diskPct": 53.0,
        "gpuTempC": 36.0,
        "gpuVramPct": 91.9
      },
      {
        "timestamp": "2026-04-25T18:30:06Z",
        "cpuPct": 3.6,
        "memoryPct": 8.1,
        "diskPct": 53.0,
        "gpuTempC": 51.0,
        "gpuVramPct": 91.9
      },
      {
        "timestamp": "2026-04-25T18:35:07Z",
        "cpuPct": 0.0,
        "memoryPct": 8.3,
        "diskPct": 53.0,
        "gpuTempC": 37.0,
        "gpuVramPct": 91.9
      },
      {
        "timestamp": "2026-04-25T18:40:10Z",
        "cpuPct": 0.0,
        "memoryPct": 8.1,
        "diskPct": 53.0,
        "gpuTempC": 37.0,
        "gpuVramPct": 91.9
      },
      {
        "timestamp": "2026-04-25T18:45:11Z",
        "cpuPct": 0.0,
        "memoryPct": 8.1,
        "diskPct": 53.0,
        "gpuTempC": 37.0,
        "gpuVramPct": 91.9
      },
      {
        "timestamp": "2026-04-25T18:50:14Z",
        "cpuPct": 0.0,
        "memoryPct": 8.0,
        "diskPct": 53.0,
        "gpuTempC": 37.0,
        "gpuVramPct": 91.9
      },
      {
        "timestamp": "2026-04-25T18:55:16Z",
        "cpuPct": 0.0,
        "memoryPct": 8.0,
        "diskPct": 53.0,
        "gpuTempC": 37.0,
        "gpuVramPct": 91.9
      },
      {
        "timestamp": "2026-04-25T19:00:19Z",
        "cpuPct": 3.6,
        "memoryPct": 8.1,
        "diskPct": 53.0,
        "gpuTempC": 53.0,
        "gpuVramPct": 91.9
      },
      {
        "timestamp": "2026-04-25T19:05:20Z",
        "cpuPct": 0.0,
        "memoryPct": 8.1,
        "diskPct": 53.0,
        "gpuTempC": 38.0,
        "gpuVramPct": 91.9
      },
      {
        "timestamp": "2026-04-25T19:10:23Z",
        "cpuPct": 0.0,
        "memoryPct": 8.1,
        "diskPct": 53.0,
        "gpuTempC": 37.0,
        "gpuVramPct": 91.9
      },
      {
        "timestamp": "2026-04-25T19:15:25Z",
        "cpuPct": 0.0,
        "memoryPct": 8.1,
        "diskPct": 53.0,
        "gpuTempC": 37.0,
        "gpuVramPct": 91.9
      },
      {
        "timestamp": "2026-04-25T19:20:26Z",
        "cpuPct": 0.3,
        "memoryPct": 8.0,
        "diskPct": 53.0,
        "gpuTempC": 38.0,
        "gpuVramPct": 91.9
      },
      {
        "timestamp": "2026-04-25T19:25:29Z",
        "cpuPct": 0.0,
        "memoryPct": 8.1,
        "diskPct": 53.0,
        "gpuTempC": 43.0,
        "gpuVramPct": 91.9
      },
      {
        "timestamp": "2026-04-25T19:30:29Z",
        "cpuPct": 0.3,
        "memoryPct": 8.1,
        "diskPct": 53.0,
        "gpuTempC": 40.0,
        "gpuVramPct": 91.9
      },
      {
        "timestamp": "2026-04-25T19:35:29Z",
        "cpuPct": 0.0,
        "memoryPct": 8.2,
        "diskPct": 53.0,
        "gpuTempC": 35.0,
        "gpuVramPct": 91.9
      },
      {
        "timestamp": "2026-04-25T19:40:30Z",
        "cpuPct": 0.0,
        "memoryPct": 8.0,
        "diskPct": 53.0,
        "gpuTempC": 35.0,
        "gpuVramPct": 91.9
      },
      {
        "timestamp": "2026-04-25T19:45:33Z",
        "cpuPct": 0.0,
        "memoryPct": 8.1,
        "diskPct": 53.0,
        "gpuTempC": 36.0,
        "gpuVramPct": 91.9
      },
      {
        "timestamp": "2026-04-25T19:50:35Z",
        "cpuPct": 0.0,
        "memoryPct": 8.1,
        "diskPct": 53.0,
        "gpuTempC": 37.0,
        "gpuVramPct": 91.9
      },
      {
        "timestamp": "2026-04-25T19:55:36Z",
        "cpuPct": 0.3,
        "memoryPct": 8.0,
        "diskPct": 53.0,
        "gpuTempC": 36.0,
        "gpuVramPct": 91.9
      },
      {
        "timestamp": "2026-04-25T20:00:39Z",
        "cpuPct": 0.0,
        "memoryPct": 8.2,
        "diskPct": 53.0,
        "gpuTempC": 38.0,
        "gpuVramPct": 91.9
      },
      {
        "timestamp": "2026-04-25T20:05:43Z",
        "cpuPct": 0.0,
        "memoryPct": 8.1,
        "diskPct": 53.0,
        "gpuTempC": 37.0,
        "gpuVramPct": 91.9
      },
      {
        "timestamp": "2026-04-25T20:10:44Z",
        "cpuPct": 0.0,
        "memoryPct": 8.1,
        "diskPct": 53.0,
        "gpuTempC": 37.0,
        "gpuVramPct": 91.9
      },
      {
        "timestamp": "2026-04-25T20:15:46Z",
        "cpuPct": 0.0,
        "memoryPct": 8.1,
        "diskPct": 53.0,
        "gpuTempC": 39.0,
        "gpuVramPct": 91.9
      },
      {
        "timestamp": "2026-04-25T20:20:48Z",
        "cpuPct": 0.0,
        "memoryPct": 8.1,
        "diskPct": 53.0,
        "gpuTempC": 38.0,
        "gpuVramPct": 91.9
      },
      {
        "timestamp": "2026-04-25T20:25:51Z",
        "cpuPct": 0.3,
        "memoryPct": 8.1,
        "diskPct": 53.0,
        "gpuTempC": 37.0,
        "gpuVramPct": 91.9
      },
      {
        "timestamp": "2026-04-25T20:30:52Z",
        "cpuPct": 3.6,
        "memoryPct": 8.1,
        "diskPct": 53.0,
        "gpuTempC": 58.0,
        "gpuVramPct": 91.9
      },
      {
        "timestamp": "2026-04-25T20:35:55Z",
        "cpuPct": 0.0,
        "memoryPct": 8.1,
        "diskPct": 53.0,
        "gpuTempC": 39.0,
        "gpuVramPct": 91.9
      },
      {
        "timestamp": "2026-04-25T20:40:56Z",
        "cpuPct": 0.3,
        "memoryPct": 8.1,
        "diskPct": 53.0,
        "gpuTempC": 38.0,
        "gpuVramPct": 91.9
      },
      {
        "timestamp": "2026-04-25T20:46:00Z",
        "cpuPct": 0.3,
        "memoryPct": 8.1,
        "diskPct": 53.0,
        "gpuTempC": 38.0,
        "gpuVramPct": 91.9
      },
      {
        "timestamp": "2026-04-25T20:51:01Z",
        "cpuPct": 0.0,
        "memoryPct": 8.1,
        "diskPct": 53.0,
        "gpuTempC": 37.0,
        "gpuVramPct": 91.9
      },
      {
        "timestamp": "2026-04-25T20:56:05Z",
        "cpuPct": 0.0,
        "memoryPct": 8.1,
        "diskPct": 53.0,
        "gpuTempC": 37.0,
        "gpuVramPct": 91.9
      }
    ],
    "disks": [
      {
        "mount": "/",
        "usedPct": 53.0,
        "freeGb": 419.0
      }
    ]
  }
}
