{
  "updatedAt": "2026-04-26T05:40:00.192279+00:00",
  "source": "kurorunner",
  "version": 1,
  "job_id": "goku-infra-health",
  "runs": [
    {
      "ts": "2026-04-26T05:40:00.192206+00:00",
      "exit": 0,
      "duration_ms": 40,
      "tokens_in": 0,
      "tokens_out": 0,
      "consecutive_errors": 0,
      "error": null
    },
    {
      "ts": "2026-04-26T05:35:00.190689+00:00",
      "exit": 0,
      "duration_ms": 39,
      "tokens_in": 0,
      "tokens_out": 0,
      "consecutive_errors": 0,
      "error": null
    },
    {
      "ts": "2026-04-26T05:30:02.922487+00:00",
      "exit": 0,
      "duration_ms": 40,
      "tokens_in": 0,
      "tokens_out": 0,
      "consecutive_errors": 0,
      "error": null
    },
    {
      "ts": "2026-04-26T05:25:05.920695+00:00",
      "exit": 0,
      "duration_ms": 40,
      "tokens_in": 0,
      "tokens_out": 0,
      "consecutive_errors": 0,
      "error": null
    },
    {
      "ts": "2026-04-26T05:20:01.689791+00:00",
      "exit": 0,
      "duration_ms": 39,
      "tokens_in": 0,
      "tokens_out": 0,
      "consecutive_errors": 0,
      "error": null
    },
    {
      "ts": "2026-04-26T05:15:01.183840+00:00",
      "exit": 0,
      "duration_ms": 40,
      "tokens_in": 0,
      "tokens_out": 0,
      "consecutive_errors": 0,
      "error": null
    },
    {
      "ts": "2026-04-26T05:10:03.929234+00:00",
      "exit": 0,
      "duration_ms": 39,
      "tokens_in": 0,
      "tokens_out": 0,
      "consecutive_errors": 0,
      "error": null
    },
    {
      "ts": "2026-04-26T05:05:00.188626+00:00",
      "exit": 0,
      "duration_ms": 40,
      "tokens_in": 0,
      "tokens_out": 0,
      "consecutive_errors": 0,
      "error": null
    },
    {
      "ts": "2026-04-26T05:00:03.188002+00:00",
      "exit": 0,
      "duration_ms": 39,
      "tokens_in": 0,
      "tokens_out": 0,
      "consecutive_errors": 0,
      "error": null
    },
    {
      "ts": "2026-04-26T04:55:02.680045+00:00",
      "exit": 0,
      "duration_ms": 38,
      "tokens_in": 0,
      "tokens_out": 0,
      "consecutive_errors": 0,
      "error": null
    },
    {
      "ts": "2026-04-26T04:50:05.685683+00:00",
      "exit": 0,
      "duration_ms": 41,
      "tokens_in": 0,
      "tokens_out": 0,
      "consecutive_errors": 0,
      "error": null
    },
    {
      "ts": "2026-04-26T04:45:01.925110+00:00",
      "exit": 0,
      "duration_ms": 39,
      "tokens_in": 0,
      "tokens_out": 0,
      "consecutive_errors": 0,
      "error": null
    },
    {
      "ts": "2026-04-26T04:40:01.189715+00:00",
      "exit": 0,
      "duration_ms": 40,
      "tokens_in": 0,
      "tokens_out": 0,
      "consecutive_errors": 0,
      "error": null
    },
    {
      "ts": "2026-04-26T04:35:04.185850+00:00",
      "exit": 0,
      "duration_ms": 40,
      "tokens_in": 0,
      "tokens_out": 0,
      "consecutive_errors": 0,
      "error": null
    },
    {
      "ts": "2026-04-26T04:30:00.431093+00:00",
      "exit": 0,
      "duration_ms": 41,
      "tokens_in": 0,
      "tokens_out": 0,
      "consecutive_errors": 0,
      "error": null
    },
    {
      "ts": "2026-04-26T04:25:03.679702+00:00",
      "exit": 0,
      "duration_ms": 34,
      "tokens_in": 0,
      "tokens_out": 0,
      "consecutive_errors": 0,
      "error": null
    },
    {
      "ts": "2026-04-26T04:20:01.563240+00:00",
      "exit": 0,
      "duration_ms": 40,
      "tokens_in": 0,
      "tokens_out": 0,
      "consecutive_errors": 0,
      "error": null
    },
    {
      "ts": "2026-04-26T04:15:05.432737+00:00",
      "exit": 0,
      "duration_ms": 40,
      "tokens_in": 0,
      "tokens_out": 0,
      "consecutive_errors": 0,
      "error": null
    },
    {
      "ts": "2026-04-26T04:10:02.434525+00:00",
      "exit": 0,
      "duration_ms": 40,
      "tokens_in": 0,
      "tokens_out": 0,
      "consecutive_errors": 0,
      "error": null
    },
    {
      "ts": "2026-04-26T04:05:00.240495+00:00",
      "exit": 0,
      "duration_ms": 40,
      "tokens_in": 0,
      "tokens_out": 0,
      "consecutive_errors": 0,
      "error": null
    }
  ]
}
