{
  "updatedAt": "2026-04-22T22:18:01.388289+00:00",
  "source": "kurorunner",
  "version": 1,
  "job_id": "goku-infra-health",
  "runs": [
    {
      "ts": "2026-04-22T22:15:04.665425+00:00",
      "exit": 0,
      "duration_ms": 47,
      "tokens_in": 0,
      "tokens_out": 0,
      "consecutive_errors": 0,
      "error": null
    },
    {
      "ts": "2026-04-22T22:10:01.664519+00:00",
      "exit": 0,
      "duration_ms": 47,
      "tokens_in": 0,
      "tokens_out": 0,
      "consecutive_errors": 0,
      "error": null
    },
    {
      "ts": "2026-04-22T22:05:04.422332+00:00",
      "exit": 0,
      "duration_ms": 50,
      "tokens_in": 0,
      "tokens_out": 0,
      "consecutive_errors": 0,
      "error": null
    },
    {
      "ts": "2026-04-22T22:00:02.905207+00:00",
      "exit": 0,
      "duration_ms": 49,
      "tokens_in": 0,
      "tokens_out": 0,
      "consecutive_errors": 0,
      "error": null
    },
    {
      "ts": "2026-04-22T21:55:05.663900+00:00",
      "exit": 0,
      "duration_ms": 32,
      "tokens_in": 0,
      "tokens_out": 0,
      "consecutive_errors": 0,
      "error": null
    },
    {
      "ts": "2026-04-22T21:50:02.394005+00:00",
      "exit": 0,
      "duration_ms": 30,
      "tokens_in": 0,
      "tokens_out": 0,
      "consecutive_errors": 0,
      "error": null
    },
    {
      "ts": "2026-04-22T21:45:00.153993+00:00",
      "exit": 0,
      "duration_ms": 32,
      "tokens_in": 0,
      "tokens_out": 0,
      "consecutive_errors": 0,
      "error": null
    },
    {
      "ts": "2026-04-22T21:40:00.136989+00:00",
      "exit": 0,
      "duration_ms": 29,
      "tokens_in": 0,
      "tokens_out": 0,
      "consecutive_errors": 0,
      "error": null
    },
    {
      "ts": "2026-04-22T21:35:00.913954+00:00",
      "exit": 0,
      "duration_ms": 48,
      "tokens_in": 0,
      "tokens_out": 0,
      "consecutive_errors": 0,
      "error": null
    },
    {
      "ts": "2026-04-22T21:30:04.150299+00:00",
      "exit": 0,
      "duration_ms": 40,
      "tokens_in": 0,
      "tokens_out": 0,
      "consecutive_errors": 0,
      "error": null
    },
    {
      "ts": "2026-04-22T21:25:02.433856+00:00",
      "exit": 0,
      "duration_ms": 62,
      "tokens_in": 0,
      "tokens_out": 0,
      "consecutive_errors": 0,
      "error": null
    },
    {
      "ts": "2026-04-22T21:20:05.166023+00:00",
      "exit": 0,
      "duration_ms": 50,
      "tokens_in": 0,
      "tokens_out": 0,
      "consecutive_errors": 0,
      "error": null
    },
    {
      "ts": "2026-04-22T21:15:02.428748+00:00",
      "exit": 0,
      "duration_ms": 63,
      "tokens_in": 0,
      "tokens_out": 0,
      "consecutive_errors": 0,
      "error": null
    },
    {
      "ts": "2026-04-22T21:10:00.429876+00:00",
      "exit": 0,
      "duration_ms": 61,
      "tokens_in": 0,
      "tokens_out": 0,
      "consecutive_errors": 0,
      "error": null
    },
    {
      "ts": "2026-04-22T21:05:03.167413+00:00",
      "exit": 0,
      "duration_ms": 52,
      "tokens_in": 0,
      "tokens_out": 0,
      "consecutive_errors": 0,
      "error": null
    },
    {
      "ts": "2026-04-22T21:00:00.922906+00:00",
      "exit": 0,
      "duration_ms": 52,
      "tokens_in": 0,
      "tokens_out": 0,
      "consecutive_errors": 0,
      "error": null
    },
    {
      "ts": "2026-04-22T20:55:01.151249+00:00",
      "exit": 0,
      "duration_ms": 32,
      "tokens_in": 0,
      "tokens_out": 0,
      "consecutive_errors": 0,
      "error": null
    },
    {
      "ts": "2026-04-22T20:50:00.301651+00:00",
      "exit": 0,
      "duration_ms": 50,
      "tokens_in": 0,
      "tokens_out": 0,
      "consecutive_errors": 0,
      "error": null
    },
    {
      "ts": "2026-04-22T20:45:00.167453+00:00",
      "exit": 0,
      "duration_ms": 49,
      "tokens_in": 0,
      "tokens_out": 0,
      "consecutive_errors": 0,
      "error": null
    },
    {
      "ts": "2026-04-22T20:40:00.152710+00:00",
      "exit": 0,
      "duration_ms": 43,
      "tokens_in": 0,
      "tokens_out": 0,
      "consecutive_errors": 0,
      "error": null
    }
  ]
}
