{
  "updatedAt": "2026-04-19T13:07:53Z",
  "source": "kurotrader-daemon",
  "version": 1,
  "data": {
    "portfolio": {
      "equity": 502.95,
      "cash": 1.75,
      "buyingPower": 1.75,
      "dayPnl": -4.14,
      "totalPnl": 2.95,
      "totalReturnPct": 0.59,
      "drawdownPct": 6.03,
      "updatedAt": "2026-04-19T13:00:31Z"
    },
    "health": {
      "cycleStatus": "healthy",
      "executionStatus": "healthy",
      "modelAgreementStatus": "healthy",
      "lastCycleAt": "2026-04-19T13:00:31Z",
      "staleCycleMinutes": 7
    },
    "topPositions": [
      {
        "symbol": "BTCUSD",
        "side": "long",
        "quantity": 0.002330421,
        "marketValue": 176.485113,
        "weightPct": 35.1,
        "unrealizedPnl": -2.676373
      },
      {
        "symbol": "ETHUSD",
        "side": "long",
        "quantity": 0.039387628,
        "marketValue": 91.853528,
        "weightPct": 18.3,
        "unrealizedPnl": -3.599142
      },
      {
        "symbol": "SOLUSD",
        "side": "long",
        "quantity": 1.450587458,
        "marketValue": 124.59966,
        "weightPct": 24.8,
        "unrealizedPnl": -5.571454
      },
      {
        "symbol": "XRPUSD",
        "side": "long",
        "quantity": 75.394576819,
        "marketValue": 108.266612,
        "weightPct": 21.5,
        "unrealizedPnl": -3.330202
      }
    ],
    "recentSignals": [
      {
        "id": "6084",
        "symbol": "SOL-USD",
        "action": "hold",
        "confidence": 0.2682,
        "generatedAt": "2026-04-19T13:00:31Z",
        "executed": false
      },
      {
        "id": "6083",
        "symbol": "XRP-USD",
        "action": "hold",
        "confidence": 0.2117,
        "generatedAt": "2026-04-19T13:00:31Z",
        "executed": false
      },
      {
        "id": "6082",
        "symbol": "ETH-USD",
        "action": "hold",
        "confidence": 0.3002,
        "generatedAt": "2026-04-19T13:00:31Z",
        "executed": false
      },
      {
        "id": "6081",
        "symbol": "BTC-USD",
        "action": "hold",
        "confidence": 0.0,
        "generatedAt": "2026-04-19T13:00:31Z",
        "executed": false
      },
      {
        "id": "6080",
        "symbol": "SOL-USD",
        "action": "hold",
        "confidence": 0.3043,
        "generatedAt": "2026-04-19T12:45:31Z",
        "executed": false
      }
    ]
  }
}
