{
  "updatedAt": "2026-04-24T03:53:47Z",
  "source": "kurotrader-daemon",
  "version": 1,
  "data": {
    "portfolio": {
      "equity": 505.38,
      "cash": 1.75,
      "buyingPower": 1.75,
      "dayPnl": -0.68,
      "totalPnl": 5.38,
      "totalReturnPct": 1.08,
      "drawdownPct": 5.58,
      "updatedAt": "2026-04-24T03:48:12Z"
    },
    "health": {
      "cycleStatus": "healthy",
      "executionStatus": "healthy",
      "modelAgreementStatus": "healthy",
      "lastCycleAt": "2026-04-24T03:48:12Z",
      "staleCycleMinutes": 5
    },
    "topPositions": [
      {
        "symbol": "BTCUSD",
        "side": "long",
        "quantity": 0.002330421,
        "marketValue": 180.883316,
        "weightPct": 35.8,
        "unrealizedPnl": 1.720809
      },
      {
        "symbol": "ETHUSD",
        "side": "long",
        "quantity": 0.039387628,
        "marketValue": 90.935745,
        "weightPct": 18.0,
        "unrealizedPnl": -4.516925
      },
      {
        "symbol": "SOLUSD",
        "side": "long",
        "quantity": 1.450587458,
        "marketValue": 123.811991,
        "weightPct": 24.5,
        "unrealizedPnl": -6.359123
      },
      {
        "symbol": "XRPUSD",
        "side": "long",
        "quantity": 75.394576819,
        "marketValue": 108.003485,
        "weightPct": 21.4,
        "unrealizedPnl": -3.593329
      }
    ],
    "recentSignals": [
      {
        "id": "7332",
        "symbol": "SOL-USD",
        "action": "buy",
        "confidence": 0.5858,
        "generatedAt": "2026-04-24T03:48:12Z",
        "executed": false
      },
      {
        "id": "7331",
        "symbol": "XRP-USD",
        "action": "buy",
        "confidence": 0.5574,
        "generatedAt": "2026-04-24T03:48:12Z",
        "executed": false
      },
      {
        "id": "7330",
        "symbol": "ETH-USD",
        "action": "buy",
        "confidence": 0.6251,
        "generatedAt": "2026-04-24T03:48:12Z",
        "executed": false
      },
      {
        "id": "7329",
        "symbol": "BTC-USD",
        "action": "hold",
        "confidence": 0.4133,
        "generatedAt": "2026-04-24T03:48:12Z",
        "executed": false
      },
      {
        "id": "7328",
        "symbol": "SOL-USD",
        "action": "buy",
        "confidence": 0.5858,
        "generatedAt": "2026-04-24T03:33:12Z",
        "executed": false
      }
    ]
  }
}
