{
  "updatedAt": "2026-04-26T03:28:22Z",
  "source": "kurotrader-daemon",
  "version": 1,
  "data": {
    "portfolio": {
      "equity": 504.65,
      "cash": 122.92,
      "buyingPower": 122.92,
      "dayPnl": -3.12,
      "totalPnl": 4.65,
      "totalReturnPct": 0.93,
      "drawdownPct": 5.71,
      "updatedAt": "2026-04-26T03:21:40Z"
    },
    "health": {
      "cycleStatus": "healthy",
      "executionStatus": "healthy",
      "modelAgreementStatus": "healthy",
      "lastCycleAt": "2026-04-26T03:21:39Z",
      "staleCycleMinutes": 6
    },
    "topPositions": [
      {
        "symbol": "BTCUSD",
        "side": "long",
        "quantity": 0.002330421,
        "marketValue": 180.60406,
        "weightPct": 35.8,
        "unrealizedPnl": 1.441553
      },
      {
        "symbol": "ETHUSD",
        "side": "long",
        "quantity": 0.021733961,
        "marketValue": 50.396709,
        "weightPct": 10.0,
        "unrealizedPnl": 0.113022
      },
      {
        "symbol": "SOLUSD",
        "side": "long",
        "quantity": 0.284326254,
        "marketValue": 24.588534,
        "weightPct": 4.9,
        "unrealizedPnl": 0.188373
      },
      {
        "symbol": "XRPUSD",
        "side": "long",
        "quantity": 88.39997342,
        "marketValue": 126.140574,
        "weightPct": 25.0,
        "unrealizedPnl": -3.976185
      }
    ],
    "recentSignals": [
      {
        "id": "7888",
        "symbol": "SOL-USD",
        "action": "hold",
        "confidence": 0.8779,
        "generatedAt": "2026-04-26T03:21:39Z",
        "executed": false
      },
      {
        "id": "7887",
        "symbol": "XRP-USD",
        "action": "hold",
        "confidence": 0.8779,
        "generatedAt": "2026-04-26T03:21:39Z",
        "executed": false
      },
      {
        "id": "7886",
        "symbol": "ETH-USD",
        "action": "hold",
        "confidence": 0.9374,
        "generatedAt": "2026-04-26T03:21:39Z",
        "executed": false
      },
      {
        "id": "7885",
        "symbol": "BTC-USD",
        "action": "hold",
        "confidence": 0.9225,
        "generatedAt": "2026-04-26T03:21:39Z",
        "executed": false
      },
      {
        "id": "7884",
        "symbol": "SOL-USD",
        "action": "hold",
        "confidence": 0.8697,
        "generatedAt": "2026-04-26T03:06:39Z",
        "executed": false
      }
    ]
  }
}
