{
  "updatedAt": "2026-04-23T19:15:21Z",
  "source": "kurotrader-daemon",
  "version": 1,
  "data": {
    "portfolio": {
      "equity": 505.65,
      "cash": 1.75,
      "buyingPower": 1.75,
      "dayPnl": -11.51,
      "totalPnl": 5.65,
      "totalReturnPct": 1.13,
      "drawdownPct": 5.53,
      "updatedAt": "2026-04-23T19:03:12Z"
    },
    "health": {
      "cycleStatus": "healthy",
      "executionStatus": "healthy",
      "modelAgreementStatus": "healthy",
      "lastCycleAt": "2026-04-23T19:03:12Z",
      "staleCycleMinutes": 12
    },
    "topPositions": [
      {
        "symbol": "BTCUSD",
        "side": "long",
        "quantity": 0.002330421,
        "marketValue": 180.857238,
        "weightPct": 35.8,
        "unrealizedPnl": 1.694731
      },
      {
        "symbol": "ETHUSD",
        "side": "long",
        "quantity": 0.039387628,
        "marketValue": 91.085859,
        "weightPct": 18.0,
        "unrealizedPnl": -4.366811
      },
      {
        "symbol": "SOLUSD",
        "side": "long",
        "quantity": 1.450587458,
        "marketValue": 123.8323,
        "weightPct": 24.5,
        "unrealizedPnl": -6.338814
      },
      {
        "symbol": "XRPUSD",
        "side": "long",
        "quantity": 75.394576819,
        "marketValue": 108.121101,
        "weightPct": 21.4,
        "unrealizedPnl": -3.475713
      }
    ],
    "recentSignals": [
      {
        "id": "7192",
        "symbol": "SOL-USD",
        "action": "buy",
        "confidence": 0.6375,
        "generatedAt": "2026-04-23T19:03:12Z",
        "executed": false
      },
      {
        "id": "7191",
        "symbol": "XRP-USD",
        "action": "hold",
        "confidence": 0.7258,
        "generatedAt": "2026-04-23T19:03:12Z",
        "executed": false
      },
      {
        "id": "7190",
        "symbol": "ETH-USD",
        "action": "buy",
        "confidence": 0.7035,
        "generatedAt": "2026-04-23T19:03:12Z",
        "executed": false
      },
      {
        "id": "7189",
        "symbol": "BTC-USD",
        "action": "buy",
        "confidence": 0.731,
        "generatedAt": "2026-04-23T19:03:12Z",
        "executed": false
      },
      {
        "id": "7188",
        "symbol": "SOL-USD",
        "action": "hold",
        "confidence": 0.0,
        "generatedAt": "2026-04-23T18:48:12Z",
        "executed": false
      }
    ]
  }
}
