{
  "updatedAt": "2026-04-21T01:42:23Z",
  "source": "kurotrader-daemon",
  "version": 1,
  "data": {
    "exposures": {
      "grossPct": 99.7,
      "netPct": 99.7,
      "longPct": 99.7,
      "shortPct": 0.0,
      "cashPct": 0.3
    },
    "positions": [
      {
        "symbol": "BTCUSD",
        "quantity": 0.002330421,
        "averagePrice": 0.0,
        "lastPrice": 0.0,
        "marketValue": 177.390947,
        "weightPct": 35.3,
        "unrealizedPnl": -1.770539,
        "side": "long"
      },
      {
        "symbol": "ETHUSD",
        "quantity": 0.039387628,
        "averagePrice": 0.0,
        "lastPrice": 0.0,
        "marketValue": 91.624682,
        "weightPct": 18.2,
        "unrealizedPnl": -3.827988,
        "side": "long"
      },
      {
        "symbol": "SOLUSD",
        "quantity": 1.450587458,
        "averagePrice": 0.0,
        "lastPrice": 0.0,
        "marketValue": 124.081801,
        "weightPct": 24.7,
        "unrealizedPnl": -6.089313,
        "side": "long"
      },
      {
        "symbol": "XRPUSD",
        "quantity": 75.394576819,
        "averagePrice": 0.0,
        "lastPrice": 0.0,
        "marketValue": 108.078126,
        "weightPct": 21.5,
        "unrealizedPnl": -3.518688,
        "side": "long"
      }
    ]
  }
}
