{
  "updatedAt": "2026-04-19T21:00:42Z",
  "source": "kurotrader-daemon",
  "version": 1,
  "data": {
    "exposures": {
      "grossPct": 99.6,
      "netPct": 99.6,
      "longPct": 99.6,
      "shortPct": 0.0,
      "cashPct": 0.4
    },
    "positions": [
      {
        "symbol": "BTCUSD",
        "quantity": 0.002330421,
        "averagePrice": 0.0,
        "lastPrice": 0.0,
        "marketValue": 173.896737,
        "weightPct": 35.1,
        "unrealizedPnl": -5.264749,
        "side": "long"
      },
      {
        "symbol": "ETHUSD",
        "quantity": 0.039387628,
        "averagePrice": 0.0,
        "lastPrice": 0.0,
        "marketValue": 89.945981,
        "weightPct": 18.2,
        "unrealizedPnl": -5.506689,
        "side": "long"
      },
      {
        "symbol": "SOLUSD",
        "quantity": 1.450587458,
        "averagePrice": 0.0,
        "lastPrice": 0.0,
        "marketValue": 123.136018,
        "weightPct": 24.9,
        "unrealizedPnl": -7.035096,
        "side": "long"
      },
      {
        "symbol": "XRPUSD",
        "quantity": 75.394576819,
        "averagePrice": 0.0,
        "lastPrice": 0.0,
        "marketValue": 106.306353,
        "weightPct": 21.5,
        "unrealizedPnl": -5.290461,
        "side": "long"
      }
    ]
  }
}
