{
  "updatedAt": "2026-04-20T21:40:53Z",
  "source": "kurotrader-daemon",
  "version": 1,
  "data": {
    "exposures": {
      "grossPct": 99.7,
      "netPct": 99.7,
      "longPct": 99.7,
      "shortPct": 0.0,
      "cashPct": 0.3
    },
    "positions": [
      {
        "symbol": "BTCUSD",
        "quantity": 0.002330421,
        "averagePrice": 0.0,
        "lastPrice": 0.0,
        "marketValue": 176.8587,
        "weightPct": 35.2,
        "unrealizedPnl": -2.302786,
        "side": "long"
      },
      {
        "symbol": "ETHUSD",
        "quantity": 0.039387628,
        "averagePrice": 0.0,
        "lastPrice": 0.0,
        "marketValue": 91.421127,
        "weightPct": 18.2,
        "unrealizedPnl": -4.031543,
        "side": "long"
      },
      {
        "symbol": "SOLUSD",
        "quantity": 1.450587458,
        "averagePrice": 0.0,
        "lastPrice": 0.0,
        "marketValue": 124.190595,
        "weightPct": 24.7,
        "unrealizedPnl": -5.980519,
        "side": "long"
      },
      {
        "symbol": "XRPUSD",
        "quantity": 75.394576819,
        "averagePrice": 0.0,
        "lastPrice": 0.0,
        "marketValue": 107.814245,
        "weightPct": 21.5,
        "unrealizedPnl": -3.782569,
        "side": "long"
      }
    ]
  }
}
