{
  "updatedAt": "2026-04-22T13:02:51Z",
  "source": "kurotrader-daemon",
  "version": 1,
  "data": {
    "exposures": {
      "grossPct": 99.7,
      "netPct": 99.7,
      "longPct": 99.7,
      "shortPct": 0.0,
      "cashPct": 0.3
    },
    "positions": [
      {
        "symbol": "BTCUSD",
        "quantity": 0.002330421,
        "averagePrice": 0.0,
        "lastPrice": 0.0,
        "marketValue": 182.469867,
        "weightPct": 35.3,
        "unrealizedPnl": 3.30736,
        "side": "long"
      },
      {
        "symbol": "ETHUSD",
        "quantity": 0.039387628,
        "averagePrice": 0.0,
        "lastPrice": 0.0,
        "marketValue": 94.733153,
        "weightPct": 18.3,
        "unrealizedPnl": -0.719517,
        "side": "long"
      },
      {
        "symbol": "SOLUSD",
        "quantity": 1.450587458,
        "averagePrice": 0.0,
        "lastPrice": 0.0,
        "marketValue": 128.739637,
        "weightPct": 24.9,
        "unrealizedPnl": -1.431477,
        "side": "long"
      },
      {
        "symbol": "XRPUSD",
        "quantity": 75.394576819,
        "averagePrice": 0.0,
        "lastPrice": 0.0,
        "marketValue": 109.653873,
        "weightPct": 21.2,
        "unrealizedPnl": -1.942941,
        "side": "long"
      }
    ]
  }
}
