{
  "updatedAt": "2026-04-22T13:38:03Z",
  "source": "kurotrader-daemon",
  "version": 1,
  "data": {
    "exposures": {
      "grossPct": 99.7,
      "netPct": 99.7,
      "longPct": 99.7,
      "shortPct": 0.0,
      "cashPct": 0.3
    },
    "positions": [
      {
        "symbol": "BTCUSD",
        "quantity": 0.002330421,
        "averagePrice": 0.0,
        "lastPrice": 0.0,
        "marketValue": 182.776317,
        "weightPct": 35.3,
        "unrealizedPnl": 3.61381,
        "side": "long"
      },
      {
        "symbol": "ETHUSD",
        "quantity": 0.039387628,
        "averagePrice": 0.0,
        "lastPrice": 0.0,
        "marketValue": 94.921623,
        "weightPct": 18.3,
        "unrealizedPnl": -0.531047,
        "side": "long"
      },
      {
        "symbol": "SOLUSD",
        "quantity": 1.450587458,
        "averagePrice": 0.0,
        "lastPrice": 0.0,
        "marketValue": 128.530752,
        "weightPct": 24.8,
        "unrealizedPnl": -1.640362,
        "side": "long"
      },
      {
        "symbol": "XRPUSD",
        "quantity": 75.394576819,
        "averagePrice": 0.0,
        "lastPrice": 0.0,
        "marketValue": 109.925293,
        "weightPct": 21.2,
        "unrealizedPnl": -1.671521,
        "side": "long"
      }
    ]
  }
}
