{
  "updatedAt": "2026-04-22T01:42:58Z",
  "source": "kurotrader-daemon",
  "version": 1,
  "data": {
    "signals": [
      {
        "id": "6788",
        "timestamp": "2026-04-22T01:30:32Z",
        "symbol": "SOL-USD",
        "action": "hold",
        "confidence": 0.3018,
        "executed": false
      },
      {
        "id": "6787",
        "timestamp": "2026-04-22T01:30:32Z",
        "symbol": "XRP-USD",
        "action": "hold",
        "confidence": 0.2989,
        "executed": false
      },
      {
        "id": "6786",
        "timestamp": "2026-04-22T01:30:32Z",
        "symbol": "ETH-USD",
        "action": "hold",
        "confidence": 0.0,
        "executed": false
      },
      {
        "id": "6785",
        "timestamp": "2026-04-22T01:30:32Z",
        "symbol": "BTC-USD",
        "action": "hold",
        "confidence": 0.5884,
        "executed": false
      },
      {
        "id": "6784",
        "timestamp": "2026-04-22T01:15:32Z",
        "symbol": "SOL-USD",
        "action": "hold",
        "confidence": 0.2826,
        "executed": false
      },
      {
        "id": "6783",
        "timestamp": "2026-04-22T01:15:32Z",
        "symbol": "XRP-USD",
        "action": "hold",
        "confidence": 0.0,
        "executed": false
      },
      {
        "id": "6782",
        "timestamp": "2026-04-22T01:15:32Z",
        "symbol": "ETH-USD",
        "action": "hold",
        "confidence": 0.4045,
        "executed": false
      },
      {
        "id": "6781",
        "timestamp": "2026-04-22T01:15:32Z",
        "symbol": "BTC-USD",
        "action": "hold",
        "confidence": 0.0,
        "executed": false
      },
      {
        "id": "6780",
        "timestamp": "2026-04-22T01:00:32Z",
        "symbol": "SOL-USD",
        "action": "hold",
        "confidence": 0.4514,
        "executed": false
      },
      {
        "id": "6779",
        "timestamp": "2026-04-22T01:00:32Z",
        "symbol": "XRP-USD",
        "action": "hold",
        "confidence": 0.2412,
        "executed": false
      }
    ]
  }
}
