{
  "updatedAt": "2026-04-21T21:26:16Z",
  "source": "kurotrader-daemon",
  "version": 1,
  "data": {
    "signals": [
      {
        "id": "6720",
        "timestamp": "2026-04-21T21:15:32Z",
        "symbol": "SOL-USD",
        "action": "hold",
        "confidence": 0.3381,
        "executed": false
      },
      {
        "id": "6719",
        "timestamp": "2026-04-21T21:15:32Z",
        "symbol": "XRP-USD",
        "action": "buy",
        "confidence": 0.6742,
        "executed": false
      },
      {
        "id": "6718",
        "timestamp": "2026-04-21T21:15:32Z",
        "symbol": "ETH-USD",
        "action": "hold",
        "confidence": 0.266,
        "executed": false
      },
      {
        "id": "6717",
        "timestamp": "2026-04-21T21:15:32Z",
        "symbol": "BTC-USD",
        "action": "hold",
        "confidence": 0.2152,
        "executed": false
      },
      {
        "id": "6716",
        "timestamp": "2026-04-21T21:00:32Z",
        "symbol": "SOL-USD",
        "action": "hold",
        "confidence": 0.229,
        "executed": false
      },
      {
        "id": "6715",
        "timestamp": "2026-04-21T21:00:32Z",
        "symbol": "XRP-USD",
        "action": "hold",
        "confidence": 0.2476,
        "executed": false
      },
      {
        "id": "6714",
        "timestamp": "2026-04-21T21:00:32Z",
        "symbol": "ETH-USD",
        "action": "hold",
        "confidence": 0.232,
        "executed": false
      },
      {
        "id": "6713",
        "timestamp": "2026-04-21T21:00:32Z",
        "symbol": "BTC-USD",
        "action": "hold",
        "confidence": 0.2091,
        "executed": false
      },
      {
        "id": "6712",
        "timestamp": "2026-04-21T20:45:32Z",
        "symbol": "SOL-USD",
        "action": "hold",
        "confidence": 0.0,
        "executed": false
      },
      {
        "id": "6711",
        "timestamp": "2026-04-21T20:45:32Z",
        "symbol": "XRP-USD",
        "action": "hold",
        "confidence": 0.2476,
        "executed": false
      }
    ]
  }
}
